README.md
setup.py
libpyn/__init__.py
libpyn/podcast.py
libpyn.egg-info/PKG-INFO
libpyn.egg-info/SOURCES.txt
libpyn.egg-info/dependency_links.txt
libpyn.egg-info/not-zip-safe
libpyn.egg-info/requires.txt
libpyn.egg-info/top_level.txt