Metadata-Version: 2.1
Name: libpyn
Version: 1.0.1
Summary: Libsyn podcast API
Home-page: https://github.com/RobbyB97/libpyn
Author: Robby Bergers
Author-email: bergersr@my.easternct.edu
License: MIT
Platform: UNKNOWN
